README.md
setup.py
keyphrasetransformer/__init__.py
keyphrasetransformer/keyphrasetransformer.py
keyphrasetransformer.egg-info/PKG-INFO
keyphrasetransformer.egg-info/SOURCES.txt
keyphrasetransformer.egg-info/dependency_links.txt
keyphrasetransformer.egg-info/requires.txt
keyphrasetransformer.egg-info/top_level.txt