Metadata-Version: 2.1
Name: keyphrasetransformer
Version: 0.0.2
Summary: Quickly extract key-phrases/topics from you text data with T5 transformer.
Home-page: https://github.com/Shivanandroy/KeyPhraseTransformer
Author: Shivanand Roy
Author-email: snrcodes@gmail.com
License: apache-2.0
Project-URL: Repo, https://github.com/Shivanandroy/KeyPhraseTransformer
Project-URL: Bug Tracker, https://github.com/Shivanandroy/KeyPhraseTransformer/issues
Keywords: keyword extraction,keyphrase extraction,keyphrase,extractionT5,simpleT5,transformers,NLP
Platform: UNKNOWN
Classifier: Intended Audience :: Developers
Classifier: Topic :: Scientific/Engineering :: Artificial Intelligence
Classifier: License :: OSI Approved :: Apache Software License
Classifier: Programming Language :: Python :: 3
Classifier: Programming Language :: Python :: 3.5
Classifier: Programming Language :: Python :: 3.6
Classifier: Programming Language :: Python :: 3.7
Classifier: Programming Language :: Python :: 3.8
Requires-Python: >=3.5
